anamod/__init__.py
anamod/core/__init__.py
anamod/core/compute_p_values.py
anamod/core/constants.py
anamod/core/feature.py
anamod/core/losses.py
anamod/core/master.py
anamod/core/model_analyzer.py
anamod/core/model_loader.py
anamod/core/perturbations.py
anamod/core/pipelines.py
anamod/core/utils.py
anamod/core/worker.py
anamod/simulation/__init__.py
anamod/simulation/__main__.py
anamod/simulation/evaluation.py
anamod/simulation/model_wrapper.py
anamod/simulation/run_trials.py
anamod/simulation/simulation.py
anamod/visualization/__init__.py
anamod/visualization/analysis.py
tests/__init__.py
tests/conftest.py
tests/gen_condor_tests.py
tests/test_baselines.py
tests/test_hierarchical.py
tests/test_temporal.py
tests/test_unit.py
tests/utils.py
tests/condor_tests/__init__.py
tests/condor_tests/test_condor_unit.py
tests/condor_tests/test_hierarchical.py
tests/condor_tests/test_temporal.py
tests/condor_tests/res/test_condor_simulation_classifier_hierarchy1.json
tests/condor_tests/res/test_condor_simulation_classifier_hierarchy2.json
tests/condor_tests/test_hierarchical/test_condor_simulation_all_pairwise_interactions_summary.json
tests/condor_tests/test_hierarchical/test_condor_simulation_clustering_hierarchy_feature_importance.csv
tests/condor_tests/test_hierarchical/test_condor_simulation_clustering_hierarchy_summary.json
tests/condor_tests/test_hierarchical/test_condor_simulation_flat_hierarchy_feature_importance.csv
tests/condor_tests/test_hierarchical/test_condor_simulation_flat_hierarchy_summary.json
tests/condor_tests/test_hierarchical/test_condor_simulation_gaussian_noise_summary.json
tests/condor_tests/test_hierarchical/test_condor_simulation_interactions_summary.json
tests/condor_tests/test_hierarchical/test_condor_simulation_noisy_interactions_summary.json
tests/condor_tests/test_hierarchical/test_condor_simulation_permutation_perturbation_feature_importance.csv
tests/condor_tests/test_hierarchical/test_condor_simulation_permutation_perturbation_summary.json
anamod-0.1.4.dist-info/LICENSE
anamod-0.1.4.dist-info/METADATA
anamod-0.1.4.dist-info/WHEEL
anamod-0.1.4.dist-info/top_level.txt
anamod-0.1.4.dist-info/zip-safe
anamod-0.1.4.dist-info/RECORD
