Metadata-Version: 2.1
Name: anamod
Version: 0.1.4
Summary: Feature Importance Analysis of Models
Home-page: https://github.com/cloudbopper/anamod
Author: Akshay Sood
Author-email: sood.iitd@gmail.com
License: MIT
Keywords: anamod
Platform: UNKNOWN
Classifier: Development Status :: 2 - Pre-Alpha
Classifier: Environment :: Console
Classifier: Intended Audience :: Science/Research
Classifier: License :: OSI Approved :: MIT License
Classifier: Programming Language :: Python :: 3.6
Classifier: Programming Language :: Python :: 3.7
Classifier: Programming Language :: Python :: 3.8
Classifier: Programming Language :: Python :: 3.9
Classifier: Programming Language :: Python :: Implementation :: CPython
Classifier: Topic :: Scientific/Engineering :: Artificial Intelligence
Requires-Python: >= 3.6
License-File: LICENSE
Requires-Dist: anytree
Requires-Dist: cloudpickle
Requires-Dist: h5py
Requires-Dist: matplotlib
Requires-Dist: numpy (>=1.19.0)
Requires-Dist: scikit-learn
Requires-Dist: scipy
Requires-Dist: seaborn
Requires-Dist: sympy
Requires-Dist: synmod
Requires-Dist: xxhash
